pyhamcrest_metamatchers/__init__.py
pyhamcrest_metamatchers/metamatchers.py
pyhamcrest_metamatchers-0.2.1.dist-info/LICENSE
pyhamcrest_metamatchers-0.2.1.dist-info/METADATA
pyhamcrest_metamatchers-0.2.1.dist-info/WHEEL
pyhamcrest_metamatchers-0.2.1.dist-info/top_level.txt
pyhamcrest_metamatchers-0.2.1.dist-info/RECORD
