Metadata-Version: 2.1
Name: pyhamcrest-metamatchers
Version: 0.2.1
Summary: A library for testing pyhamcrest matchers.
Home-page: https://github.com/ibolit/pyhamcrest_metamatchers
Author: Timofey Danshin
Author-email: t.danshin@gmail.com
License: BSD
Platform: UNKNOWN
Classifier: Environment :: Console
Classifier: Intended Audience :: Developers
Classifier: Natural Language :: English
Classifier: License :: OSI Approved :: BSD License
Classifier: Programming Language :: Python :: 3.4
Classifier: Programming Language :: Python :: 3.5
Classifier: Programming Language :: Python :: 3.6
Classifier: Programming Language :: Python :: Implementation :: CPython
Classifier: Programming Language :: Python :: Implementation :: PyPy
Classifier: Topic :: Software Development
Requires-Python: >=3.4
Requires-Dist: pyhamcrest (>=1.9)
